Metadata-Version: 2.1
Name: maxdev
Version: 1.4.2
Summary: MaxDev is a helpful library for developers.
Home-page: 
Author: maxeqx
Author-email: maxeqxmail@gmail.com
License: MIT
Keywords: maxdev maxeqx mdev dev developer
Classifier: Development Status :: 5 - Production/Stable
Classifier: Intended Audience :: Education
Classifier: Operating System :: Microsoft :: Windows :: Windows 11
Classifier: License :: OSI Approved :: MIT License
Classifier: Programming Language :: Python :: 3
License-File: LICENSE.txt
Requires-Dist: requests
Requires-Dist: datetime
